<?xml version='1.0' encoding='UTF-8'?>
<!-- Created with Fritzing (http://www.fritzing.org/) -->
<netlist date="Thu Sep 19 21:43:04 2019" sketch="id257_Experiment_2_0.fz">
 <net>
  <connector name="Pin 4" id="connector3">
   <part label="S4" id="10628490" title="Pushbutton"/>
  </connector>
  <connector name="Pin 3" id="connector2">
   <part label="S4" id="10628490" title="Pushbutton"/>
  </connector>
  <connector name="Pin 4" id="connector3">
   <part label="S3" id="10628470" title="Pushbutton"/>
  </connector>
  <connector name="Pin 3" id="connector2">
   <part label="S3" id="10628470" title="Pushbutton"/>
  </connector>
  <connector name="+5V" id="connector18">
   <part label="Arduino1" id="10536860" title="Arduino"/>
  </connector>
 </net>
 <net>
  <connector name="Pin 1" id="connector0">
   <part label="S4" id="10628490" title="Pushbutton"/>
  </connector>
  <connector name="D7" id="connector8">
   <part label="Arduino1" id="10536860" title="Arduino"/>
  </connector>
  <connector name="Pin 2" id="connector1">
   <part label="S4" id="10628490" title="Pushbutton"/>
  </connector>
  <connector name="Pin 1" id="connector1">
   <part label="R3" id="10635030" title="10k Ω Resistor"/>
  </connector>
 </net>
 <net>
  <connector name="Pin 0" id="connector0">
   <part label="R3" id="10635030" title="10k Ω Resistor"/>
  </connector>
  <connector name="Pin 0" id="connector0">
   <part label="R2" id="10630390" title="10k Ω Resistor"/>
  </connector>
  <connector name="Pin 2" id="connector1">
   <part label="S2" id="10542710" title="Pushbutton"/>
  </connector>
  <connector name="Pin 2" id="connector1">
   <part label="S1" id="10542440" title="Pushbutton"/>
  </connector>
  <connector name="pin8" id="connector7">
   <part label="IC1" id="10535670" title="WTV020-SD"/>
  </connector>
  <connector name="Pin 1" id="connector0">
   <part label="S2" id="10542710" title="Pushbutton"/>
  </connector>
  <connector name="Pin 1" id="connector0">
   <part label="S1" id="10542440" title="Pushbutton"/>
  </connector>
  <connector name="GND" id="connector20">
   <part label="Arduino1" id="10536860" title="Arduino"/>
  </connector>
  <connector name="GND" id="connector19">
   <part label="Arduino1" id="10536860" title="Arduino"/>
  </connector>
  <connector name="GND" id="connector1">
   <part label="Arduino1" id="10536860" title="Arduino"/>
  </connector>
 </net>
 <net>
  <connector name="Pin 1" id="connector0">
   <part label="S3" id="10628470" title="Pushbutton"/>
  </connector>
  <connector name="D6" id="connector9">
   <part label="Arduino1" id="10536860" title="Arduino"/>
  </connector>
  <connector name="Pin 2" id="connector1">
   <part label="S3" id="10628470" title="Pushbutton"/>
  </connector>
  <connector name="Pin 1" id="connector1">
   <part label="R2" id="10630390" title="10k Ω Resistor"/>
  </connector>
 </net>
 <net>
  <connector name="pin1" id="connector0">
   <part label="SPKR1" id="10546670" title="Loudspeaker"/>
  </connector>
  <connector name="pin5" id="connector4">
   <part label="IC1" id="10535670" title="WTV020-SD"/>
  </connector>
 </net>
 <net>
  <connector name="pin2" id="connector1">
   <part label="SPKR1" id="10546670" title="Loudspeaker"/>
  </connector>
  <connector name="pin4" id="connector3">
   <part label="IC1" id="10535670" title="WTV020-SD"/>
  </connector>
 </net>
 <net>
  <connector name="pin16" id="connector15">
   <part label="IC1" id="10535670" title="WTV020-SD"/>
  </connector>
  <connector name="Pin 1" id="connector1">
   <part label="R1" id="10539260" title="470 Ω Resistor"/>
  </connector>
  <connector name="3V3" id="connector17">
   <part label="Arduino1" id="10536860" title="Arduino"/>
  </connector>
 </net>
 <net>
  <connector name="D5" id="connector10">
   <part label="Arduino1" id="10536860" title="Arduino"/>
  </connector>
  <connector name="pin15" id="connector14">
   <part label="IC1" id="10535670" title="WTV020-SD"/>
  </connector>
  <connector name="cathode" id="connector0">
   <part label="LED1" id="10541320" title="white smd LED"/>
  </connector>
 </net>
 <net>
  <connector name="pin10" id="connector9">
   <part label="IC1" id="10535670" title="WTV020-SD"/>
  </connector>
  <connector name="D4" id="connector11">
   <part label="Arduino1" id="10536860" title="Arduino"/>
  </connector>
 </net>
 <net>
  <connector name="pin7" id="connector6">
   <part label="IC1" id="10535670" title="WTV020-SD"/>
  </connector>
  <connector name="D3" id="connector12">
   <part label="Arduino1" id="10536860" title="Arduino"/>
  </connector>
 </net>
 <net>
  <connector name="pin1" id="connector0">
   <part label="IC1" id="10535670" title="WTV020-SD"/>
  </connector>
  <connector name="D2" id="connector13">
   <part label="Arduino1" id="10536860" title="Arduino"/>
  </connector>
 </net>
 <net>
  <connector name="pin12" id="connector11">
   <part label="IC1" id="10535670" title="WTV020-SD"/>
  </connector>
  <connector name="Pin 3" id="connector2">
   <part label="S2" id="10542710" title="Pushbutton"/>
  </connector>
  <connector name="Pin 4" id="connector3">
   <part label="S2" id="10542710" title="Pushbutton"/>
  </connector>
 </net>
 <net>
  <connector name="pin13" id="connector12">
   <part label="IC1" id="10535670" title="WTV020-SD"/>
  </connector>
  <connector name="Pin 3" id="connector2">
   <part label="S1" id="10542440" title="Pushbutton"/>
  </connector>
  <connector name="Pin 4" id="connector3">
   <part label="S1" id="10542440" title="Pushbutton"/>
  </connector>
 </net>
 <net>
  <connector name="anode" id="connector1">
   <part label="LED1" id="10541320" title="white smd LED"/>
  </connector>
  <connector name="Pin 0" id="connector0">
   <part label="R1" id="10539260" title="470 Ω Resistor"/>
  </connector>
 </net>
 <net>
  <connector name="pin14" id="connector13">
   <part label="IC1" id="10535670" title="WTV020-SD"/>
  </connector>
 </net>
 <net>
  <connector name="pin9" id="connector8">
   <part label="IC1" id="10535670" title="WTV020-SD"/>
  </connector>
 </net>
 <net>
  <connector name="pin11" id="connector10">
   <part label="IC1" id="10535670" title="WTV020-SD"/>
  </connector>
 </net>
 <net>
  <connector name="pin6" id="connector5">
   <part label="IC1" id="10535670" title="WTV020-SD"/>
  </connector>
 </net>
 <net>
  <connector name="pin3" id="connector2">
   <part label="IC1" id="10535670" title="WTV020-SD"/>
  </connector>
 </net>
 <net>
  <connector name="pin2" id="connector1">
   <part label="IC1" id="10535670" title="WTV020-SD"/>
  </connector>
 </net>
 <net>
  <connector name="A2" id="connector24">
   <part label="Arduino1" id="10536860" title="Arduino"/>
  </connector>
 </net>
 <net>
  <connector name="A1" id="connector23">
   <part label="Arduino1" id="10536860" title="Arduino"/>
  </connector>
 </net>
 <net>
  <connector name="A0" id="connector22">
   <part label="Arduino1" id="10536860" title="Arduino"/>
  </connector>
 </net>
 <net>
  <connector name="VIN" id="connector21">
   <part label="Arduino1" id="10536860" title="Arduino"/>
  </connector>
 </net>
 <net>
  <connector name="D8" id="connector7">
   <part label="Arduino1" id="10536860" title="Arduino"/>
  </connector>
 </net>
 <net>
  <connector name="D9" id="connector6">
   <part label="Arduino1" id="10536860" title="Arduino"/>
  </connector>
 </net>
 <net>
  <connector name="D10" id="connector5">
   <part label="Arduino1" id="10536860" title="Arduino"/>
  </connector>
 </net>
 <net>
  <connector name="D11" id="connector4">
   <part label="Arduino1" id="10536860" title="Arduino"/>
  </connector>
 </net>
 <net>
  <connector name="D12" id="connector3">
   <part label="Arduino1" id="10536860" title="Arduino"/>
  </connector>
 </net>
 <net>
  <connector name="D13" id="connector2">
   <part label="Arduino1" id="10536860" title="Arduino"/>
  </connector>
 </net>
 <net>
  <connector name="aref" id="connector0">
   <part label="Arduino1" id="10536860" title="Arduino"/>
  </connector>
 </net>
 <net>
  <connector name="RST" id="connector16">
   <part label="Arduino1" id="10536860" title="Arduino"/>
  </connector>
 </net>
 <net>
  <connector name="D0RX" id="connector15">
   <part label="Arduino1" id="10536860" title="Arduino"/>
  </connector>
 </net>
 <net>
  <connector name="D1TX" id="connector14">
   <part label="Arduino1" id="10536860" title="Arduino"/>
  </connector>
 </net>
 <net>
  <connector name="A5" id="connector27">
   <part label="Arduino1" id="10536860" title="Arduino"/>
  </connector>
 </net>
 <net>
  <connector name="A4" id="connector26">
   <part label="Arduino1" id="10536860" title="Arduino"/>
  </connector>
 </net>
 <net>
  <connector name="A3" id="connector25">
   <part label="Arduino1" id="10536860" title="Arduino"/>
  </connector>
 </net>
</netlist>
