<?xml version='1.0' encoding='UTF-8'?>
<!-- Created with Fritzing (http://www.fritzing.org/) -->
<netlist date="Wed Sep 18 20:30:01 2019" sketch="id2973_ping_pongv1_0.fz">
 <net>
  <connector name="C" id="connector3">
   <part id="854105780" title="7-SEGMENT-DISPLAY-1_-RED" label="U4"/>
  </connector>
 </net>
 <net>
  <connector name="D" id="connector1">
   <part id="854105780" title="7-SEGMENT-DISPLAY-1_-RED" label="U4"/>
  </connector>
 </net>
 <net>
  <connector name="E" id="connector0">
   <part id="854105780" title="7-SEGMENT-DISPLAY-1_-RED" label="U4"/>
  </connector>
 </net>
 <net>
  <connector name="Pin 1" id="connector0">
   <part id="29580" title="Pushbutton" label="S1"/>
  </connector>
  <connector name="Pin 3" id="connector2">
   <part id="29580" title="Pushbutton" label="S1"/>
  </connector>
  <connector name="Pin 2" id="connector1">
   <part id="29580" title="Pushbutton" label="S1"/>
  </connector>
  <connector name="Pin 4" id="connector3">
   <part id="29580" title="Pushbutton" label="S1"/>
  </connector>
  <connector name="Pin 4" id="connector3">
   <part id="29610" title="Pushbutton" label="S2"/>
  </connector>
  <connector name="Pin 2" id="connector1">
   <part id="29610" title="Pushbutton" label="S2"/>
  </connector>
  <connector name="Pin 3" id="connector2">
   <part id="29610" title="Pushbutton" label="S2"/>
  </connector>
  <connector name="Pin 1" id="connector0">
   <part id="29610" title="Pushbutton" label="S2"/>
  </connector>
  <connector name="Pin 0" id="connector0">
   <part id="21190" title="1kΩ Resistor" label="R4"/>
  </connector>
  <connector name="Pin 0" id="connector0">
   <part id="26770" title="1kΩ Resistor" label="R26"/>
  </connector>
 </net>
 <net>
  <connector name="cathode" id="connector0">
   <part id="30490" title="Red (633nm) LED" label="LED4"/>
  </connector>
  <connector name="cathode" id="connector0">
   <part id="37770" title="Red (633nm) LED" label="LED7"/>
  </connector>
  <connector name="cathode" id="connector0">
   <part id="30520" title="Red (633nm) LED" label="LED5"/>
  </connector>
  <connector name="cathode" id="connector0">
   <part id="30430" title="Red (633nm) LED" label="LED2"/>
  </connector>
  <connector name="cathode" id="connector0">
   <part id="30550" title="Red (633nm) LED" label="LED6"/>
  </connector>
  <connector name="Pin 1" id="connector1">
   <part id="43510" title="1kΩ Resistor" label="R28"/>
  </connector>
 </net>
 <net>
  <connector name="C" id="connector3">
   <part id="854105610" title="7-SEGMENT-DISPLAY-1_-RED" label="U3"/>
  </connector>
 </net>
 <net>
  <connector name="D" id="connector1">
   <part id="854105610" title="7-SEGMENT-DISPLAY-1_-RED" label="U3"/>
  </connector>
 </net>
 <net>
  <connector name="E" id="connector0">
   <part id="854105610" title="7-SEGMENT-DISPLAY-1_-RED" label="U3"/>
  </connector>
 </net>
 <net>
  <connector name="G2" id="connector7">
   <part id="854105780" title="7-SEGMENT-DISPLAY-1_-RED" label="U4"/>
  </connector>
  <connector name="G2" id="connector7">
   <part id="854105610" title="7-SEGMENT-DISPLAY-1_-RED" label="U3"/>
  </connector>
  <connector name="Pin 0" id="connector0">
   <part id="43510" title="1kΩ Resistor" label="R28"/>
  </connector>
 </net>
 <net>
  <connector name="Pin 1" id="connector1">
   <part id="26770" title="1kΩ Resistor" label="R26"/>
  </connector>
 </net>
 <net>
  <connector name="F" id="connector8">
   <part id="854105780" title="7-SEGMENT-DISPLAY-1_-RED" label="U4"/>
  </connector>
 </net>
 <net>
  <connector name="G" id="connector9">
   <part id="854105780" title="7-SEGMENT-DISPLAY-1_-RED" label="U4"/>
  </connector>
 </net>
 <net>
  <connector name="B" id="connector5">
   <part id="854105780" title="7-SEGMENT-DISPLAY-1_-RED" label="U4"/>
  </connector>
 </net>
 <net>
  <connector name="A" id="connector6">
   <part id="854105780" title="7-SEGMENT-DISPLAY-1_-RED" label="U4"/>
  </connector>
 </net>
 <net>
  <connector name="Pin 1" id="connector1">
   <part id="24130" title="1kΩ Resistor" label="R12"/>
  </connector>
 </net>
 <net>
  <connector name="Pin 1" id="connector1">
   <part id="23730" title="1kΩ Resistor" label="R10"/>
  </connector>
 </net>
 <net>
  <connector name="Pin 0" id="connector0">
   <part id="854106760" title="220Ω Resistor" label="R29"/>
  </connector>
 </net>
 <net>
  <connector name="Pin 1" id="connector1">
   <part id="25270" title="1kΩ Resistor" label="R19"/>
  </connector>
 </net>
 <net>
  <connector name="Pin 1" id="connector1">
   <part id="23550" title="1kΩ Resistor" label="R9"/>
  </connector>
 </net>
 <net>
  <connector name="Pin 1" id="connector1">
   <part id="23310" title="1kΩ Resistor" label="R7"/>
  </connector>
 </net>
 <net>
  <connector name="F" id="connector8">
   <part id="854105610" title="7-SEGMENT-DISPLAY-1_-RED" label="U3"/>
  </connector>
 </net>
 <net>
  <connector name="G" id="connector9">
   <part id="854105610" title="7-SEGMENT-DISPLAY-1_-RED" label="U3"/>
  </connector>
 </net>
 <net>
  <connector name="A" id="connector6">
   <part id="854105610" title="7-SEGMENT-DISPLAY-1_-RED" label="U3"/>
  </connector>
 </net>
 <net>
  <connector name="Pin 1" id="connector1">
   <part id="24550" title="1kΩ Resistor" label="R15"/>
  </connector>
 </net>
 <net>
  <connector name="B" id="connector5">
   <part id="854105610" title="7-SEGMENT-DISPLAY-1_-RED" label="U3"/>
  </connector>
 </net>
 <net>
  <connector name="Pin 1" id="connector1">
   <part id="21190" title="1kΩ Resistor" label="R4"/>
  </connector>
 </net>
 <net>
  <connector name="Pin 1" id="connector1">
   <part id="854106760" title="220Ω Resistor" label="R29"/>
  </connector>
 </net>
 <net>
  <connector name="DP" id="connector4">
   <part id="854105780" title="7-SEGMENT-DISPLAY-1_-RED" label="U4"/>
  </connector>
 </net>
 <net>
  <connector name="G1" id="connector2">
   <part id="854105780" title="7-SEGMENT-DISPLAY-1_-RED" label="U4"/>
  </connector>
 </net>
 <net>
  <connector name="DP" id="connector4">
   <part id="854105610" title="7-SEGMENT-DISPLAY-1_-RED" label="U3"/>
  </connector>
 </net>
 <net>
  <connector name="G1" id="connector2">
   <part id="854105610" title="7-SEGMENT-DISPLAY-1_-RED" label="U3"/>
  </connector>
 </net>
 <net>
  <connector name="anode" id="connector1">
   <part id="37770" title="Red (633nm) LED" label="LED7"/>
  </connector>
  <connector name="Pin 0" id="connector0">
   <part id="25270" title="1kΩ Resistor" label="R19"/>
  </connector>
 </net>
 <net>
  <connector name="Pin 0" id="connector0">
   <part id="23310" title="1kΩ Resistor" label="R7"/>
  </connector>
  <connector name="anode" id="connector1">
   <part id="30430" title="Red (633nm) LED" label="LED2"/>
  </connector>
 </net>
 <net>
  <connector name="Pin 0" id="connector0">
   <part id="24130" title="1kΩ Resistor" label="R12"/>
  </connector>
  <connector name="anode" id="connector1">
   <part id="30520" title="Red (633nm) LED" label="LED5"/>
  </connector>
 </net>
 <net>
  <connector name="Pin 0" id="connector0">
   <part id="24550" title="1kΩ Resistor" label="R15"/>
  </connector>
  <connector name="anode" id="connector1">
   <part id="30550" title="Red (633nm) LED" label="LED6"/>
  </connector>
 </net>
 <net>
  <connector name="Pin 0" id="connector0">
   <part id="23730" title="1kΩ Resistor" label="R10"/>
  </connector>
  <connector name="anode" id="connector1">
   <part id="30490" title="Red (633nm) LED" label="LED4"/>
  </connector>
 </net>
 <net>
  <connector name="Pin 0" id="connector0">
   <part id="23550" title="1kΩ Resistor" label="R9"/>
  </connector>
  <connector name="anode" id="connector1">
   <part id="30460" title="Red (633nm) LED" label="LED3"/>
  </connector>
 </net>
 <net>
  <connector name="cathode" id="connector0">
   <part id="30460" title="Red (633nm) LED" label="LED3"/>
  </connector>
 </net>
</netlist>
