<?xml version='1.0' encoding='UTF-8'?>
<!-- Created with Fritzing (http://www.fritzing.org/) -->
<netlist date="Wed Sep 18 20:12:24 2019" sketch="id2905_4x4x4_Matrix_2_routed2_1_0.fz">
 <net>
  <connector id="connector12" name="pin13">
   <part id="1422200" title="Generic single row SMD female header - 13 pins" label="J65"/>
  </connector>
  <connector id="connector0" name="pin1">
   <part id="1421080" title="Generic female header - 1 pins" label="J19"/>
  </connector>
  <connector id="connector0" name="pin1">
   <part id="1421410" title="Generic female header - 1 pins" label="J36"/>
  </connector>
  <connector id="connector0" name="pin1">
   <part id="1420840" title="Generic female header - 1 pins" label="J7"/>
  </connector>
  <connector id="connector0" name="pin1">
   <part id="1421470" title="Generic female header - 1 pins" label="J42"/>
  </connector>
 </net>
 <net>
  <connector id="connector0" name="pin1">
   <part id="1421490" title="Generic female header - 1 pins" label="J44"/>
  </connector>
  <connector id="connector0" name="pin1">
   <part id="1421610" title="Generic female header - 1 pins" label="J56"/>
  </connector>
  <connector id="connector0" name="pin1">
   <part id="1420970" title="Generic female header - 1 pins" label="J16"/>
  </connector>
  <connector id="connector5" name="pin6">
   <part id="1422220" title="Generic single row SMD female header - 13 pins" label="J66"/>
  </connector>
  <connector id="connector0" name="pin1">
   <part id="1421180" title="Generic female header - 1 pins" label="J29"/>
  </connector>
 </net>
 <net>
  <connector id="connector0" name="pin1">
   <part id="1421460" title="Generic female header - 1 pins" label="J41"/>
  </connector>
  <connector id="connector0" name="pin1">
   <part id="1421190" title="Generic female header - 1 pins" label="J30"/>
  </connector>
  <connector id="connector0" name="pin1">
   <part id="1420950" title="Generic female header - 1 pins" label="J14"/>
  </connector>
  <connector id="connector0" name="pin1">
   <part id="1421540" title="Generic female header - 1 pins" label="J49"/>
  </connector>
  <connector id="connector10" name="pin11">
   <part id="1422200" title="Generic single row SMD female header - 13 pins" label="J65"/>
  </connector>
 </net>
 <net>
  <connector id="connector0" name="pin1">
   <part id="1420790" title="Generic female header - 1 pins" label="J4"/>
  </connector>
  <connector id="connector0" name="pin1">
   <part id="1421100" title="Generic female header - 1 pins" label="J21"/>
  </connector>
  <connector id="connector6" name="pin7">
   <part id="1422220" title="Generic single row SMD female header - 13 pins" label="J66"/>
  </connector>
  <connector id="connector0" name="pin1">
   <part id="1421440" title="Generic female header - 1 pins" label="J39"/>
  </connector>
  <connector id="connector0" name="pin1">
   <part id="1421400" title="Generic female header - 1 pins" label="J35"/>
  </connector>
 </net>
 <net>
  <connector id="connector0" name="pin1">
   <part id="1420930" title="Generic female header - 1 pins" label="J12"/>
  </connector>
  <connector id="connector4" name="pin5">
   <part id="1422220" title="Generic single row SMD female header - 13 pins" label="J66"/>
  </connector>
  <connector id="connector0" name="pin1">
   <part id="1421150" title="Generic female header - 1 pins" label="J26"/>
  </connector>
  <connector id="connector0" name="pin1">
   <part id="1421630" title="Generic female header - 1 pins" label="J58"/>
  </connector>
  <connector id="connector0" name="pin1">
   <part id="1421520" title="Generic female header - 1 pins" label="J47"/>
  </connector>
 </net>
 <net>
  <connector id="connector0" name="pin1">
   <part id="1422220" title="Generic single row SMD female header - 13 pins" label="J66"/>
  </connector>
  <connector id="connector0" name="pin1">
   <part id="1420780" title="Generic female header - 1 pins" label="J3"/>
  </connector>
  <connector id="connector0" name="pin1">
   <part id="1421580" title="Generic female header - 1 pins" label="J53"/>
  </connector>
  <connector id="connector0" name="pin1">
   <part id="1421170" title="Generic female header - 1 pins" label="J28"/>
  </connector>
  <connector id="connector0" name="pin1">
   <part id="1421550" title="Generic female header - 1 pins" label="J50"/>
  </connector>
 </net>
 <net>
  <connector id="connector0" name="pin1">
   <part id="1421160" title="Generic female header - 1 pins" label="J27"/>
  </connector>
  <connector id="connector0" name="pin1">
   <part id="1420850" title="Generic female header - 1 pins" label="J8"/>
  </connector>
  <connector id="connector3" name="pin4">
   <part id="1422220" title="Generic single row SMD female header - 13 pins" label="J66"/>
  </connector>
  <connector id="connector0" name="pin1">
   <part id="1421390" title="Generic female header - 1 pins" label="J34"/>
  </connector>
  <connector id="connector0" name="pin1">
   <part id="1421480" title="Generic female header - 1 pins" label="J43"/>
  </connector>
 </net>
 <net>
  <connector id="connector6" name="pin7">
   <part id="1422200" title="Generic single row SMD female header - 13 pins" label="J65"/>
  </connector>
  <connector id="connector0" name="pin1">
   <part id="1421110" title="Generic female header - 1 pins" label="J22"/>
  </connector>
  <connector id="connector0" name="pin1">
   <part id="1421530" title="Generic female header - 1 pins" label="J48"/>
  </connector>
  <connector id="connector0" name="pin1">
   <part id="1420960" title="Generic female header - 1 pins" label="J15"/>
  </connector>
  <connector id="connector0" name="pin1">
   <part id="1421600" title="Generic female header - 1 pins" label="J55"/>
  </connector>
 </net>
 <net>
  <connector id="connector7" name="pin8">
   <part id="1422200" title="Generic single row SMD female header - 13 pins" label="J65"/>
  </connector>
  <connector id="connector0" name="pin1">
   <part id="1421070" title="Generic female header - 1 pins" label="J18"/>
  </connector>
  <connector id="connector0" name="pin1">
   <part id="1420910" title="Generic female header - 1 pins" label="J10"/>
  </connector>
  <connector id="connector0" name="pin1">
   <part id="1421590" title="Generic female header - 1 pins" label="J54"/>
  </connector>
  <connector id="connector0" name="pin1">
   <part id="1421640" title="Generic female header - 1 pins" label="J59"/>
  </connector>
 </net>
 <net>
  <connector id="connector5" name="pin6">
   <part id="1422200" title="Generic single row SMD female header - 13 pins" label="J65"/>
  </connector>
  <connector id="connector0" name="pin1">
   <part id="1420920" title="Generic female header - 1 pins" label="J11"/>
  </connector>
  <connector id="connector0" name="pin1">
   <part id="1420820" title="Generic female header - 1 pins" label="J5"/>
  </connector>
  <connector id="connector0" name="pin1">
   <part id="1420940" title="Generic female header - 1 pins" label="J13"/>
  </connector>
  <connector id="connector0" name="pin1">
   <part id="1420720" title="Generic female header - 1 pins" label="J1"/>
  </connector>
 </net>
 <net>
  <connector id="connector2" name="pin3">
   <part id="1422200" title="Generic single row SMD female header - 13 pins" label="J65"/>
  </connector>
  <connector id="connector0" name="pin1">
   <part id="1421420" title="Generic female header - 1 pins" label="J37"/>
  </connector>
  <connector id="connector0" name="pin1">
   <part id="1421690" title="Generic female header - 1 pins" label="J64"/>
  </connector>
  <connector id="connector0" name="pin1">
   <part id="1421500" title="Generic female header - 1 pins" label="J45"/>
  </connector>
  <connector id="connector0" name="pin1">
   <part id="1421680" title="Generic female header - 1 pins" label="J63"/>
  </connector>
 </net>
 <net>
  <connector id="connector3" name="pin4">
   <part id="1422200" title="Generic single row SMD female header - 13 pins" label="J65"/>
  </connector>
  <connector id="connector0" name="pin1">
   <part id="1421660" title="Generic female header - 1 pins" label="J61"/>
  </connector>
  <connector id="connector0" name="pin1">
   <part id="1421650" title="Generic female header - 1 pins" label="J60"/>
  </connector>
  <connector id="connector0" name="pin1">
   <part id="1421670" title="Generic female header - 1 pins" label="J62"/>
  </connector>
  <connector id="connector0" name="pin1">
   <part id="1421450" title="Generic female header - 1 pins" label="J40"/>
  </connector>
 </net>
 <net>
  <connector id="connector0" name="pin1">
   <part id="1421130" title="Generic female header - 1 pins" label="J24"/>
  </connector>
  <connector id="connector0" name="pin1">
   <part id="1421140" title="Generic female header - 1 pins" label="J25"/>
  </connector>
  <connector id="connector0" name="pin1">
   <part id="1421200" title="Generic female header - 1 pins" label="J31"/>
  </connector>
  <connector id="connector0" name="pin1">
   <part id="1421210" title="Generic female header - 1 pins" label="J32"/>
  </connector>
  <connector id="connector4" name="pin5">
   <part id="1422200" title="Generic single row SMD female header - 13 pins" label="J65"/>
  </connector>
 </net>
 <net>
  <connector id="connector9" name="pin10">
   <part id="1422200" title="Generic single row SMD female header - 13 pins" label="J65"/>
  </connector>
  <connector id="connector0" name="pin1">
   <part id="1421060" title="Generic female header - 1 pins" label="J17"/>
  </connector>
  <connector id="connector0" name="pin1">
   <part id="1421560" title="Generic female header - 1 pins" label="J51"/>
  </connector>
  <connector id="connector0" name="pin1">
   <part id="1420760" title="Generic female header - 1 pins" label="J2"/>
  </connector>
  <connector id="connector0" name="pin1">
   <part id="1421570" title="Generic female header - 1 pins" label="J52"/>
  </connector>
 </net>
 <net>
  <connector id="connector0" name="pin1">
   <part id="1421380" title="Generic female header - 1 pins" label="J33"/>
  </connector>
  <connector id="connector8" name="pin9">
   <part id="1422200" title="Generic single row SMD female header - 13 pins" label="J65"/>
  </connector>
  <connector id="connector0" name="pin1">
   <part id="1421430" title="Generic female header - 1 pins" label="J38"/>
  </connector>
  <connector id="connector0" name="pin1">
   <part id="1421090" title="Generic female header - 1 pins" label="J20"/>
  </connector>
  <connector id="connector0" name="pin1">
   <part id="1420830" title="Generic female header - 1 pins" label="J6"/>
  </connector>
 </net>
 <net>
  <connector id="connector0" name="pin1">
   <part id="1421620" title="Generic female header - 1 pins" label="J57"/>
  </connector>
  <connector id="connector0" name="pin1">
   <part id="1421120" title="Generic female header - 1 pins" label="J23"/>
  </connector>
  <connector id="connector0" name="pin1">
   <part id="1420900" title="Generic female header - 1 pins" label="J9"/>
  </connector>
  <connector id="connector0" name="pin1">
   <part id="1421510" title="Generic female header - 1 pins" label="J46"/>
  </connector>
  <connector id="connector11" name="pin12">
   <part id="1422200" title="Generic single row SMD female header - 13 pins" label="J65"/>
  </connector>
 </net>
 <net>
  <connector id="connector1" name="pin2">
   <part id="1422200" title="Generic single row SMD female header - 13 pins" label="J65"/>
  </connector>
 </net>
 <net>
  <connector id="connector0" name="pin1">
   <part id="1422200" title="Generic single row SMD female header - 13 pins" label="J65"/>
  </connector>
 </net>
 <net>
  <connector id="connector12" name="pin13">
   <part id="1422220" title="Generic single row SMD female header - 13 pins" label="J66"/>
  </connector>
 </net>
 <net>
  <connector id="connector10" name="pin11">
   <part id="1422220" title="Generic single row SMD female header - 13 pins" label="J66"/>
  </connector>
 </net>
 <net>
  <connector id="connector1" name="pin2">
   <part id="1422220" title="Generic single row SMD female header - 13 pins" label="J66"/>
  </connector>
 </net>
 <net>
  <connector id="connector11" name="pin12">
   <part id="1422220" title="Generic single row SMD female header - 13 pins" label="J66"/>
  </connector>
 </net>
 <net>
  <connector id="connector7" name="pin8">
   <part id="1422220" title="Generic single row SMD female header - 13 pins" label="J66"/>
  </connector>
 </net>
 <net>
  <connector id="connector2" name="pin3">
   <part id="1422220" title="Generic single row SMD female header - 13 pins" label="J66"/>
  </connector>
 </net>
 <net>
  <connector id="connector8" name="pin9">
   <part id="1422220" title="Generic single row SMD female header - 13 pins" label="J66"/>
  </connector>
 </net>
 <net>
  <connector id="connector9" name="pin10">
   <part id="1422220" title="Generic single row SMD female header - 13 pins" label="J66"/>
  </connector>
 </net>
</netlist>
