<?xml version='1.0' encoding='UTF-8'?>
<!-- Created with Fritzing (http://www.fritzing.org/) -->
<netlist date="Wed Sep 18 21:59:00 2019" sketch="id3241_Quaduino_0.fz">
 <net>
  <connector name="Pin 1" id="connector0">
   <part label="S1" id="370220" title="Pushbutton"/>
  </connector>
  <connector name="Pin 2" id="connector1">
   <part label="S1" id="370220" title="Pushbutton"/>
  </connector>
  <connector name="Pin 1" id="connector1">
   <part label="R1" id="372160" title="10k立 Resistor"/>
  </connector>
  <connector name="1" id="connector1">
   <part label="C3" id="372390" title="Ceramic Capacitor"/>
  </connector>
  <connector name="pin1" id="connector0">
   <part label="J6" id="389690" title="Generic female header - 14 pins"/>
  </connector>
  <connector name="RESET" id="connector0">
   <part label="CPU" id="430880" title="atmega168"/>
  </connector>
 </net>
 <net>
  <connector name="pin3" id="connector2">
   <part label="USB" id="370170" title="Generic female header - 6 pins"/>
  </connector>
  <connector name="Pin 0" id="connector0">
   <part label="R1" id="372160" title="10k立 Resistor"/>
  </connector>
  <connector name="pin7" id="connector6">
   <part label="J6" id="389690" title="Generic female header - 14 pins"/>
  </connector>
  <connector name="AVCC" id="connector19">
   <part label="CPU" id="430880" title="atmega168"/>
  </connector>
  <connector name="pin1" id="connector0">
   <part label="PWR" id="382900" title="Generic female header - 2 pins"/>
  </connector>
  <connector name="Pin 1" id="connector1">
   <part label="R2" id="372640" title="220立 Resistor"/>
  </connector>
  <connector name="VCC" id="connector6">
   <part label="CPU" id="430880" title="atmega168"/>
  </connector>
  <connector name="pin9" id="connector8">
   <part label="J5" id="387720" title="Generic female header - 14 pins"/>
  </connector>
 </net>
 <net>
  <connector name="pin2" id="connector1">
   <part label="PWR" id="382900" title="Generic female header - 2 pins"/>
  </connector>
  <connector name="1" id="connector1">
   <part label="C2" id="370470" title="Ceramic Capacitor"/>
  </connector>
  <connector name="GND" id="connector21">
   <part label="CPU" id="430880" title="atmega168"/>
  </connector>
  <connector name="cathode" id="connector0">
   <part label="LED" id="372610" title="Red (633nm) LED"/>
  </connector>
  <connector name="1" id="connector1">
   <part label="C1" id="370440" title="Ceramic Capacitor"/>
  </connector>
  <connector name="pin7" id="connector6">
   <part label="J5" id="387720" title="Generic female header - 14 pins"/>
  </connector>
  <connector name="pin8" id="connector7">
   <part label="J6" id="389690" title="Generic female header - 14 pins"/>
  </connector>
  <connector name="Pin 3" id="connector2">
   <part label="S1" id="370220" title="Pushbutton"/>
  </connector>
  <connector name="pin1" id="connector0">
   <part label="USB" id="370170" title="Generic female header - 6 pins"/>
  </connector>
  <connector name="Pin 4" id="connector3">
   <part label="S1" id="370220" title="Pushbutton"/>
  </connector>
  <connector name="GND" id="connector7">
   <part label="CPU" id="430880" title="atmega168"/>
  </connector>
 </net>
 <net>
  <connector name="pin 1" id="connector1">
   <part label="16MHz" id="370270" title="Crystal"/>
  </connector>
  <connector name="pin10" id="connector9">
   <part label="J6" id="389690" title="Generic female header - 14 pins"/>
  </connector>
  <connector name="0" id="connector0">
   <part label="C2" id="370470" title="Ceramic Capacitor"/>
  </connector>
  <connector name="XLAT2" id="connector9">
   <part label="CPU" id="430880" title="atmega168"/>
  </connector>
 </net>
 <net>
  <connector name="pin9" id="connector8">
   <part label="J6" id="389690" title="Generic female header - 14 pins"/>
  </connector>
  <connector name="pin 0" id="connector0">
   <part label="16MHz" id="370270" title="Crystal"/>
  </connector>
  <connector name="XLAT1" id="connector8">
   <part label="CPU" id="430880" title="atmega168"/>
  </connector>
  <connector name="0" id="connector0">
   <part label="C1" id="370440" title="Ceramic Capacitor"/>
  </connector>
 </net>
 <net>
  <connector name="Pin 0" id="connector0">
   <part label="R2" id="372640" title="220立 Resistor"/>
  </connector>
  <connector name="anode" id="connector1">
   <part label="LED" id="372610" title="Red (633nm) LED"/>
  </connector>
 </net>
 <net>
  <connector name="0" id="connector0">
   <part label="C3" id="372390" title="Ceramic Capacitor"/>
  </connector>
  <connector name="pin6" id="connector5">
   <part label="USB" id="370170" title="Generic female header - 6 pins"/>
  </connector>
 </net>
 <net>
  <connector name="D5 (PWM)" id="connector10">
   <part label="CPU" id="430880" title="atmega168"/>
  </connector>
  <connector name="pin11" id="connector10">
   <part label="J6" id="389690" title="Generic female header - 14 pins"/>
  </connector>
 </net>
 <net>
  <connector name="D6 (PWM)" id="connector11">
   <part label="CPU" id="430880" title="atmega168"/>
  </connector>
  <connector name="pin12" id="connector11">
   <part label="J6" id="389690" title="Generic female header - 14 pins"/>
  </connector>
 </net>
 <net>
  <connector name="D7" id="connector12">
   <part label="CPU" id="430880" title="atmega168"/>
  </connector>
  <connector name="pin13" id="connector12">
   <part label="J6" id="389690" title="Generic female header - 14 pins"/>
  </connector>
 </net>
 <net>
  <connector name="D8" id="connector13">
   <part label="CPU" id="430880" title="atmega168"/>
  </connector>
  <connector name="pin14" id="connector13">
   <part label="J6" id="389690" title="Generic female header - 14 pins"/>
  </connector>
 </net>
 <net>
  <connector name="pin12" id="connector11">
   <part label="J5" id="387720" title="Generic female header - 14 pins"/>
  </connector>
  <connector name="D11 (PWM)" id="connector16">
   <part label="CPU" id="430880" title="atmega168"/>
  </connector>
 </net>
 <net>
  <connector name="pin13" id="connector12">
   <part label="J5" id="387720" title="Generic female header - 14 pins"/>
  </connector>
  <connector name="D10 (PWM)" id="connector15">
   <part label="CPU" id="430880" title="atmega168"/>
  </connector>
 </net>
 <net>
  <connector name="pin14" id="connector13">
   <part label="J5" id="387720" title="Generic female header - 14 pins"/>
  </connector>
  <connector name="D9 (PWM)" id="connector14">
   <part label="CPU" id="430880" title="atmega168"/>
  </connector>
 </net>
 <net>
  <connector name="D0 (RX)" id="connector1">
   <part label="CPU" id="430880" title="atmega168"/>
  </connector>
  <connector name="pin2" id="connector1">
   <part label="J6" id="389690" title="Generic female header - 14 pins"/>
  </connector>
  <connector name="pin4" id="connector3">
   <part label="USB" id="370170" title="Generic female header - 6 pins"/>
  </connector>
 </net>
 <net>
  <connector name="D1 (TX)" id="connector2">
   <part label="CPU" id="430880" title="atmega168"/>
  </connector>
  <connector name="pin3" id="connector2">
   <part label="J6" id="389690" title="Generic female header - 14 pins"/>
  </connector>
  <connector name="pin5" id="connector4">
   <part label="USB" id="370170" title="Generic female header - 6 pins"/>
  </connector>
 </net>
 <net>
  <connector name="D2" id="connector3">
   <part label="CPU" id="430880" title="atmega168"/>
  </connector>
  <connector name="pin4" id="connector3">
   <part label="J6" id="389690" title="Generic female header - 14 pins"/>
  </connector>
 </net>
 <net>
  <connector name="D3 (PWM)" id="connector4">
   <part label="CPU" id="430880" title="atmega168"/>
  </connector>
  <connector name="pin5" id="connector4">
   <part label="J6" id="389690" title="Generic female header - 14 pins"/>
  </connector>
 </net>
 <net>
  <connector name="pin8" id="connector7">
   <part label="J5" id="387720" title="Generic female header - 14 pins"/>
  </connector>
  <connector name="AREF" id="connector20">
   <part label="CPU" id="430880" title="atmega168"/>
  </connector>
 </net>
 <net>
  <connector name="D4" id="connector5">
   <part label="CPU" id="430880" title="atmega168"/>
  </connector>
  <connector name="pin6" id="connector5">
   <part label="J6" id="389690" title="Generic female header - 14 pins"/>
  </connector>
 </net>
 <net>
  <connector name="pin2" id="connector1">
   <part label="J5" id="387720" title="Generic female header - 14 pins"/>
  </connector>
  <connector name="A4" id="connector26">
   <part label="CPU" id="430880" title="atmega168"/>
  </connector>
 </net>
 <net>
  <connector name="pin3" id="connector2">
   <part label="J5" id="387720" title="Generic female header - 14 pins"/>
  </connector>
  <connector name="A3" id="connector25">
   <part label="CPU" id="430880" title="atmega168"/>
  </connector>
 </net>
 <net>
  <connector name="pin4" id="connector3">
   <part label="J5" id="387720" title="Generic female header - 14 pins"/>
  </connector>
  <connector name="A2" id="connector24">
   <part label="CPU" id="430880" title="atmega168"/>
  </connector>
 </net>
 <net>
  <connector name="pin5" id="connector4">
   <part label="J5" id="387720" title="Generic female header - 14 pins"/>
  </connector>
  <connector name="A1" id="connector23">
   <part label="CPU" id="430880" title="atmega168"/>
  </connector>
 </net>
 <net>
  <connector name="pin6" id="connector5">
   <part label="J5" id="387720" title="Generic female header - 14 pins"/>
  </connector>
  <connector name="A0" id="connector22">
   <part label="CPU" id="430880" title="atmega168"/>
  </connector>
 </net>
 <net>
  <connector name="pin10" id="connector9">
   <part label="J5" id="387720" title="Generic female header - 14 pins"/>
  </connector>
  <connector name="D13" id="connector18">
   <part label="CPU" id="430880" title="atmega168"/>
  </connector>
 </net>
 <net>
  <connector name="pin11" id="connector10">
   <part label="J5" id="387720" title="Generic female header - 14 pins"/>
  </connector>
  <connector name="D12" id="connector17">
   <part label="CPU" id="430880" title="atmega168"/>
  </connector>
 </net>
 <net>
  <connector name="pin1" id="connector0">
   <part label="J5" id="387720" title="Generic female header - 14 pins"/>
  </connector>
  <connector name="A5" id="connector27">
   <part label="CPU" id="430880" title="atmega168"/>
  </connector>
 </net>
 <net>
  <connector name="pin2" id="connector1">
   <part label="USB" id="370170" title="Generic female header - 6 pins"/>
  </connector>
 </net>
</netlist>
