<?xml version='1.0' encoding='UTF-8'?>
<!-- Created with Fritzing (http://www.fritzing.org/) -->
<netlist sketch="id3973_stepprv1_0.fz" date="Thu Sep 19 01:17:35 2019">
 <net>
  <connector id="connector1" name="D0">
   <part id="74950" title="Teensy 3.0" label="Teensy1"/>
  </connector>
  <connector id="connector2" name="2">
   <part id="74010" title="SWITCH-MOMENTARY-2" label="S10"/>
  </connector>
 </net>
 <net>
  <connector id="connector2" name="2">
   <part id="74030" title="SWITCH-MOMENTARY-2" label="S12"/>
  </connector>
  <connector id="connector8" name="D7">
   <part id="74950" title="Teensy 3.0" label="Teensy1"/>
  </connector>
 </net>
 <net>
  <connector id="connector2" name="2">
   <part id="74000" title="SWITCH-MOMENTARY-2" label="S9"/>
  </connector>
  <connector id="connector7" name="D6">
   <part id="74950" title="Teensy 3.0" label="Teensy1"/>
  </connector>
 </net>
 <net>
  <connector id="connector2" name="2">
   <part id="74060" title="SWITCH-MOMENTARY-2" label="S15"/>
  </connector>
  <connector id="connector6" name="D5">
   <part id="74950" title="Teensy 3.0" label="Teensy1"/>
  </connector>
 </net>
 <net>
  <connector id="connector2" name="2">
   <part id="74050" title="SWITCH-MOMENTARY-2" label="S14"/>
  </connector>
  <connector id="connector5" name="D4">
   <part id="74950" title="Teensy 3.0" label="Teensy1"/>
  </connector>
 </net>
 <net>
  <connector id="connector2" name="2">
   <part id="74020" title="SWITCH-MOMENTARY-2" label="S11"/>
  </connector>
  <connector id="connector4" name="D3">
   <part id="74950" title="Teensy 3.0" label="Teensy1"/>
  </connector>
 </net>
 <net>
  <connector id="connector2" name="2">
   <part id="74040" title="SWITCH-MOMENTARY-2" label="S13"/>
  </connector>
  <connector id="connector3" name="D2">
   <part id="74950" title="Teensy 3.0" label="Teensy1"/>
  </connector>
 </net>
 <net>
  <connector id="connector2" name="D1">
   <part id="74950" title="Teensy 3.0" label="Teensy1"/>
  </connector>
  <connector id="connector2" name="2">
   <part id="74140" title="SWITCH-MOMENTARY-2" label="S16"/>
  </connector>
 </net>
 <net>
  <connector id="connector9" name="D8">
   <part id="74950" title="Teensy 3.0" label="Teensy1"/>
  </connector>
  <connector id="connector2" name="2">
   <part id="73830" title="SWITCH-MOMENTARY-2" label="S1"/>
  </connector>
 </net>
 <net>
  <connector id="connector10" name="D9">
   <part id="74950" title="Teensy 3.0" label="Teensy1"/>
  </connector>
  <connector id="connector2" name="2">
   <part id="73860" title="SWITCH-MOMENTARY-2" label="S2"/>
  </connector>
 </net>
 <net>
  <connector id="connector11" name="D10">
   <part id="74950" title="Teensy 3.0" label="Teensy1"/>
  </connector>
  <connector id="connector2" name="2">
   <part id="73880" title="SWITCH-MOMENTARY-2" label="S3"/>
  </connector>
 </net>
 <net>
  <connector id="connector12" name="D11">
   <part id="74950" title="Teensy 3.0" label="Teensy1"/>
  </connector>
  <connector id="connector2" name="2">
   <part id="73900" title="SWITCH-MOMENTARY-2" label="S4"/>
  </connector>
 </net>
 <net>
  <connector id="connector13" name="D12">
   <part id="74950" title="Teensy 3.0" label="Teensy1"/>
  </connector>
  <connector id="connector2" name="2">
   <part id="73930" title="SWITCH-MOMENTARY-2" label="S6"/>
  </connector>
 </net>
 <net>
  <connector id="connector19" name="D13">
   <part id="74950" title="Teensy 3.0" label="Teensy1"/>
  </connector>
  <connector id="connector2" name="2">
   <part id="73920" title="SWITCH-MOMENTARY-2" label="S5"/>
  </connector>
 </net>
 <net>
  <connector id="connector20" name="A0/D14">
   <part id="74950" title="Teensy 3.0" label="Teensy1"/>
  </connector>
  <connector id="connector2" name="2">
   <part id="73950" title="SWITCH-MOMENTARY-2" label="S8"/>
  </connector>
 </net>
 <net>
  <connector id="connector21" name="A1/D15">
   <part id="74950" title="Teensy 3.0" label="Teensy1"/>
  </connector>
  <connector id="connector2" name="2">
   <part id="73940" title="SWITCH-MOMENTARY-2" label="S7"/>
  </connector>
 </net>
 <net>
  <connector id="connector2" name="2">
   <part id="74160" title="SWITCH-MOMENTARY-2" label="S17"/>
  </connector>
  <connector id="connector22" name="A2/D16">
   <part id="74950" title="Teensy 3.0" label="Teensy1"/>
  </connector>
 </net>
 <net>
  <connector id="connector2" name="2">
   <part id="74170" title="SWITCH-MOMENTARY-2" label="S18"/>
  </connector>
  <connector id="connector23" name="A3/D17">
   <part id="74950" title="Teensy 3.0" label="Teensy1"/>
  </connector>
 </net>
 <net>
  <connector id="connector24" name="A4/D18">
   <part id="74950" title="Teensy 3.0" label="Teensy1"/>
  </connector>
  <connector id="connector2" name="2">
   <part id="74180" title="SWITCH-MOMENTARY-2" label="S19"/>
  </connector>
 </net>
 <net>
  <connector id="connector0" name="1">
   <part id="74030" title="SWITCH-MOMENTARY-2" label="S12"/>
  </connector>
  <connector id="connector0" name="1">
   <part id="73940" title="SWITCH-MOMENTARY-2" label="S7"/>
  </connector>
  <connector id="connector0" name="1">
   <part id="74020" title="SWITCH-MOMENTARY-2" label="S11"/>
  </connector>
  <connector id="connector0" name="1">
   <part id="74180" title="SWITCH-MOMENTARY-2" label="S19"/>
  </connector>
  <connector id="connector0" name="1">
   <part id="73950" title="SWITCH-MOMENTARY-2" label="S8"/>
  </connector>
  <connector id="connector0" name="1">
   <part id="74160" title="SWITCH-MOMENTARY-2" label="S17"/>
  </connector>
  <connector id="connector0" name="1">
   <part id="73930" title="SWITCH-MOMENTARY-2" label="S6"/>
  </connector>
  <connector id="connector16" name="GND">
   <part id="74950" title="Teensy 3.0" label="Teensy1"/>
  </connector>
  <connector id="connector0" name="1">
   <part id="73900" title="SWITCH-MOMENTARY-2" label="S4"/>
  </connector>
  <connector id="connector0" name="GND">
   <part id="74950" title="Teensy 3.0" label="Teensy1"/>
  </connector>
  <connector id="connector0" name="1">
   <part id="74010" title="SWITCH-MOMENTARY-2" label="S10"/>
  </connector>
  <connector id="connector0" name="1">
   <part id="74170" title="SWITCH-MOMENTARY-2" label="S18"/>
  </connector>
  <connector id="connector0" name="1">
   <part id="74050" title="SWITCH-MOMENTARY-2" label="S14"/>
  </connector>
  <connector id="connector0" name="1">
   <part id="73830" title="SWITCH-MOMENTARY-2" label="S1"/>
  </connector>
  <connector id="connector0" name="1">
   <part id="73920" title="SWITCH-MOMENTARY-2" label="S5"/>
  </connector>
  <connector id="connector0" name="1">
   <part id="74000" title="SWITCH-MOMENTARY-2" label="S9"/>
  </connector>
  <connector id="connector0" name="1">
   <part id="73880" title="SWITCH-MOMENTARY-2" label="S3"/>
  </connector>
  <connector id="connector0" name="1">
   <part id="73860" title="SWITCH-MOMENTARY-2" label="S2"/>
  </connector>
  <connector id="connector0" name="1">
   <part id="74040" title="SWITCH-MOMENTARY-2" label="S13"/>
  </connector>
  <connector id="connector0" name="1">
   <part id="74060" title="SWITCH-MOMENTARY-2" label="S15"/>
  </connector>
  <connector id="connector0" name="1">
   <part id="74140" title="SWITCH-MOMENTARY-2" label="S16"/>
  </connector>
 </net>
 <net>
  <connector id="connector0" name="E">
   <part id="74890" title="POT" label="U7"/>
  </connector>
  <connector id="connector32" name="Vin">
   <part id="74950" title="Teensy 3.0" label="Teensy1"/>
  </connector>
  <connector id="connector0" name="E">
   <part id="74880" title="POT" label="U6"/>
  </connector>
  <connector id="connector0" name="E">
   <part id="74870" title="POT" label="U5"/>
  </connector>
  <connector id="connector0" name="E">
   <part id="74900" title="POT" label="U8"/>
  </connector>
 </net>
 <net>
  <connector id="connector31" name="AGND">
   <part id="74950" title="Teensy 3.0" label="Teensy1"/>
  </connector>
  <connector id="connector2" name="A">
   <part id="74880" title="POT" label="U6"/>
  </connector>
  <connector id="connector2" name="A">
   <part id="74890" title="POT" label="U7"/>
  </connector>
  <connector id="connector2" name="A">
   <part id="74870" title="POT" label="U5"/>
  </connector>
  <connector id="connector2" name="A">
   <part id="74900" title="POT" label="U8"/>
  </connector>
 </net>
 <net>
  <connector id="connector25" name="A5/D19">
   <part id="74950" title="Teensy 3.0" label="Teensy1"/>
  </connector>
  <connector id="connector1" name="S">
   <part id="74880" title="POT" label="U6"/>
  </connector>
 </net>
 <net>
  <connector id="connector26" name="A6/D20">
   <part id="74950" title="Teensy 3.0" label="Teensy1"/>
  </connector>
  <connector id="connector1" name="S">
   <part id="74900" title="POT" label="U8"/>
  </connector>
 </net>
 <net>
  <connector id="connector27" name="A7/D21">
   <part id="74950" title="Teensy 3.0" label="Teensy1"/>
  </connector>
  <connector id="connector1" name="S">
   <part id="74890" title="POT" label="U7"/>
  </connector>
 </net>
 <net>
  <connector id="connector28" name="A8/D22">
   <part id="74950" title="Teensy 3.0" label="Teensy1"/>
  </connector>
  <connector id="connector1" name="S">
   <part id="74870" title="POT" label="U5"/>
  </connector>
 </net>
 <net>
  <connector id="connector35" name="AREF">
   <part id="74950" title="Teensy 3.0" label="Teensy1"/>
  </connector>
 </net>
 <net>
  <connector id="connector18" name="Reset">
   <part id="74950" title="Teensy 3.0" label="Teensy1"/>
  </connector>
 </net>
 <net>
  <connector id="connector29" name="A9/D23">
   <part id="74950" title="Teensy 3.0" label="Teensy1"/>
  </connector>
 </net>
 <net>
  <connector id="connector36" name="VUSB">
   <part id="74950" title="Teensy 3.0" label="Teensy1"/>
  </connector>
 </net>
 <net>
  <connector id="connector15" name="3V3">
   <part id="74950" title="Teensy 3.0" label="Teensy1"/>
  </connector>
 </net>
 <net>
  <connector id="connector33" name="A11">
   <part id="74950" title="Teensy 3.0" label="Teensy1"/>
  </connector>
 </net>
 <net>
  <connector id="connector30" name="3V3">
   <part id="74950" title="Teensy 3.0" label="Teensy1"/>
  </connector>
  <connector id="connector14" name="VBat">
   <part id="74950" title="Teensy 3.0" label="Teensy1"/>
  </connector>
 </net>
 <net>
  <connector id="connector34" name="A10">
   <part id="74950" title="Teensy 3.0" label="Teensy1"/>
  </connector>
 </net>
 <net>
  <connector id="connector17" name="Program">
   <part id="74950" title="Teensy 3.0" label="Teensy1"/>
  </connector>
 </net>
</netlist>
