<?xml version='1.0' encoding='UTF-8'?>
<!-- Created with Fritzing (http://www.fritzing.org/) -->
<netlist sketch="id472_ON_OFF_con_Arduino_GSM_Shield_0.fz" date="Thu Sep 19 04:49:47 2019">
 <net>
  <connector id="connector87" name="5V">
   <part label="Componente1" title="Arduino Uno (Rev3)" id="20360"/>
  </connector>
 </net>
 <net>
  <connector id="connector1" name="Pin 1">
   <part label="R2" title="220立 Resistor" id="18247440"/>
  </connector>
  <connector id="connector1" name="Pin 1">
   <part label="R1" title="220立 Resistor" id="20420"/>
  </connector>
  <connector id="connector57" name="GND">
   <part label="Componente1" title="Arduino Uno (Rev3)" id="20360"/>
  </connector>
  <connector id="connector89" name="GND">
   <part label="Componente1" title="Arduino Uno (Rev3)" id="20360"/>
  </connector>
  <connector id="connector88" name="GND">
   <part label="Componente1" title="Arduino Uno (Rev3)" id="20360"/>
  </connector>
 </net>
 <net>
  <connector id="connector53" name="D10 PWM/SS">
   <part label="Componente1" title="Arduino Uno (Rev3)" id="20360"/>
  </connector>
  <connector id="connector1" name="anode">
   <part label="LED1" title="Red (660nm) LED" id="20390"/>
  </connector>
 </net>
 <net>
  <connector id="connector55" name="D12/MISO">
   <part label="Componente1" title="Arduino Uno (Rev3)" id="20360"/>
  </connector>
  <connector id="connector1" name="anode">
   <part label="LED2" title="Green (570nm) LED" id="18247320"/>
  </connector>
 </net>
 <net>
  <connector id="connector0" name="Pin 0">
   <part label="R1" title="220立 Resistor" id="20420"/>
  </connector>
  <connector id="connector0" name="cathode">
   <part label="LED1" title="Red (660nm) LED" id="20390"/>
  </connector>
 </net>
 <net>
  <connector id="connector0" name="Pin 0">
   <part label="R2" title="220立 Resistor" id="18247440"/>
  </connector>
  <connector id="connector0" name="cathode">
   <part label="LED2" title="Green (570nm) LED" id="18247320"/>
  </connector>
 </net>
 <net>
  <connector id="connector45" name="MISO/D12">
   <part label="Componente2" title="Arduino GSM Shield" id="18247570"/>
  </connector>
 </net>
 <net>
  <connector id="connector63" name="PWM D5">
   <part label="Componente2" title="Arduino GSM Shield" id="18247570"/>
  </connector>
 </net>
 <net>
  <connector id="connector70" name="A4/SDA">
   <part label="Componente2" title="Arduino GSM Shield" id="18247570"/>
  </connector>
  <connector id="connector41" name="A4/SDA">
   <part label="Componente2" title="Arduino GSM Shield" id="18247570"/>
  </connector>
 </net>
 <net>
  <connector id="connector52" name="RST ARDUINO">
   <part label="Componente2" title="Arduino GSM Shield" id="18247570"/>
  </connector>
 </net>
 <net>
  <connector id="connector67" name="A1">
   <part label="Componente2" title="Arduino GSM Shield" id="18247570"/>
  </connector>
 </net>
 <net>
  <connector id="connector48" name="PWM D9">
   <part label="Componente2" title="Arduino GSM Shield" id="18247570"/>
  </connector>
 </net>
 <net>
  <connector id="connector50" name="N/C">
   <part label="Componente2" title="Arduino GSM Shield" id="18247570"/>
  </connector>
 </net>
 <net>
  <connector id="connector44" name="SCK/D13">
   <part label="Componente2" title="Arduino GSM Shield" id="18247570"/>
  </connector>
 </net>
 <net>
  <connector id="connector68" name="A2">
   <part label="Componente2" title="Arduino GSM Shield" id="18247570"/>
  </connector>
 </net>
 <net>
  <connector id="connector46" name="MOSI/PWM D11">
   <part label="Componente2" title="Arduino GSM Shield" id="18247570"/>
  </connector>
 </net>
 <net>
  <connector id="connector65" name="RST MDM/D7">
   <part label="Componente2" title="Arduino GSM Shield" id="18247570"/>
  </connector>
 </net>
 <net>
  <connector id="connector55" name="AGND">
   <part label="Componente2" title="Arduino GSM Shield" id="18247570"/>
  </connector>
  <connector id="connector43" name="AGND">
   <part label="Componente2" title="Arduino GSM Shield" id="18247570"/>
  </connector>
  <connector id="connector56" name="AGND">
   <part label="Componente2" title="Arduino GSM Shield" id="18247570"/>
  </connector>
 </net>
 <net>
  <connector id="connector47" name="SS/PWM D10">
   <part label="Componente2" title="Arduino GSM Shield" id="18247570"/>
  </connector>
 </net>
 <net>
  <connector id="connector59" name="N/C D1">
   <part label="Componente2" title="Arduino GSM Shield" id="18247570"/>
  </connector>
 </net>
 <net>
  <connector id="connector61" name="DSM TX D3">
   <part label="Componente2" title="Arduino GSM Shield" id="18247570"/>
  </connector>
 </net>
 <net>
  <connector id="connector51" name="IOREF">
   <part label="Componente2" title="Arduino GSM Shield" id="18247570"/>
  </connector>
 </net>
 <net>
  <connector id="connector71" name="A5/SCL">
   <part label="Componente2" title="Arduino GSM Shield" id="18247570"/>
  </connector>
  <connector id="connector40" name="A5/SCL">
   <part label="Componente2" title="Arduino GSM Shield" id="18247570"/>
  </connector>
 </net>
 <net>
  <connector id="connector53" name="3V3">
   <part label="Componente2" title="Arduino GSM Shield" id="18247570"/>
  </connector>
 </net>
 <net>
  <connector id="connector58" name="N/C D0">
   <part label="Componente2" title="Arduino GSM Shield" id="18247570"/>
  </connector>
 </net>
 <net>
  <connector id="connector62" name="PWM D4">
   <part label="Componente2" title="Arduino GSM Shield" id="18247570"/>
  </connector>
 </net>
 <net>
  <connector id="connector49" name="D8">
   <part label="Componente2" title="Arduino GSM Shield" id="18247570"/>
  </connector>
 </net>
 <net>
  <connector id="connector66" name="A0">
   <part label="Componente2" title="Arduino GSM Shield" id="18247570"/>
  </connector>
 </net>
 <net>
  <connector id="connector60" name="DSM RX D2">
   <part label="Componente2" title="Arduino GSM Shield" id="18247570"/>
  </connector>
 </net>
 <net>
  <connector id="connector54" name="5V">
   <part label="Componente2" title="Arduino GSM Shield" id="18247570"/>
  </connector>
 </net>
 <net>
  <connector id="connector57" name="VIN">
   <part label="Componente2" title="Arduino GSM Shield" id="18247570"/>
  </connector>
 </net>
 <net>
  <connector id="connector42" name="AREF">
   <part label="Componente2" title="Arduino GSM Shield" id="18247570"/>
  </connector>
 </net>
 <net>
  <connector id="connector64" name="PWM D6">
   <part label="Componente2" title="Arduino GSM Shield" id="18247570"/>
  </connector>
 </net>
 <net>
  <connector id="connector69" name="A3">
   <part label="Componente2" title="Arduino GSM Shield" id="18247570"/>
  </connector>
 </net>
 <net>
  <connector id="connector4" name="A4/SDA">
   <part label="Componente1" title="Arduino Uno (Rev3)" id="20360"/>
  </connector>
  <connector id="connector59" name="A4/SDA">
   <part label="Componente1" title="Arduino Uno (Rev3)" id="20360"/>
  </connector>
 </net>
 <net>
  <connector id="connector51" name="D8">
   <part label="Componente1" title="Arduino Uno (Rev3)" id="20360"/>
  </connector>
 </net>
 <net>
  <connector id="connector64" name="D3 PWM">
   <part label="Componente1" title="Arduino Uno (Rev3)" id="20360"/>
  </connector>
 </net>
 <net>
  <connector id="connector66" name="D5 PWM">
   <part label="Componente1" title="Arduino Uno (Rev3)" id="20360"/>
  </connector>
 </net>
 <net>
  <connector id="connector56" name="D13/SCK">
   <part label="Componente1" title="Arduino Uno (Rev3)" id="20360"/>
  </connector>
 </net>
 <net>
  <connector id="connector67" name="D6 PWM">
   <part label="Componente1" title="Arduino Uno (Rev3)" id="20360"/>
  </connector>
 </net>
 <net>
  <connector id="connector61" name="D0/RX">
   <part label="Componente1" title="Arduino Uno (Rev3)" id="20360"/>
  </connector>
 </net>
 <net>
  <connector id="connector84" name="ioref">
   <part label="Componente1" title="Arduino Uno (Rev3)" id="20360"/>
  </connector>
 </net>
 <net>
  <connector id="connector52" name="D9 PWM">
   <part label="Componente1" title="Arduino Uno (Rev3)" id="20360"/>
  </connector>
 </net>
 <net>
  <connector id="connector58" name="AREF">
   <part label="Componente1" title="Arduino Uno (Rev3)" id="20360"/>
  </connector>
 </net>
 <net>
  <connector id="connector3" name="A3">
   <part label="Componente1" title="Arduino Uno (Rev3)" id="20360"/>
  </connector>
 </net>
 <net>
  <connector id="connector85" name="RESET">
   <part label="Componente1" title="Arduino Uno (Rev3)" id="20360"/>
  </connector>
 </net>
 <net>
  <connector id="connector5" name="A5/SCL">
   <part label="Componente1" title="Arduino Uno (Rev3)" id="20360"/>
  </connector>
  <connector id="connector60" name="A5/SCL">
   <part label="Componente1" title="Arduino Uno (Rev3)" id="20360"/>
  </connector>
 </net>
 <net>
  <connector id="connector90" name="VIN">
   <part label="Componente1" title="Arduino Uno (Rev3)" id="20360"/>
  </connector>
 </net>
 <net>
  <connector id="connector62" name="D1/TX">
   <part label="Componente1" title="Arduino Uno (Rev3)" id="20360"/>
  </connector>
 </net>
 <net>
  <connector id="connector65" name="D4">
   <part label="Componente1" title="Arduino Uno (Rev3)" id="20360"/>
  </connector>
 </net>
 <net>
  <connector id="connector86" name="3V3">
   <part label="Componente1" title="Arduino Uno (Rev3)" id="20360"/>
  </connector>
 </net>
 <net>
  <connector id="connector0" name="A0">
   <part label="Componente1" title="Arduino Uno (Rev3)" id="20360"/>
  </connector>
 </net>
 <net>
  <connector id="connector54" name="D11 PWM/MOSI">
   <part label="Componente1" title="Arduino Uno (Rev3)" id="20360"/>
  </connector>
 </net>
 <net>
  <connector id="connector91" name="N/C">
   <part label="Componente1" title="Arduino Uno (Rev3)" id="20360"/>
  </connector>
 </net>
 <net>
  <connector id="connector2" name="A2">
   <part label="Componente1" title="Arduino Uno (Rev3)" id="20360"/>
  </connector>
 </net>
 <net>
  <connector id="connector63" name="D2">
   <part label="Componente1" title="Arduino Uno (Rev3)" id="20360"/>
  </connector>
 </net>
 <net>
  <connector id="connector68" name="D7">
   <part label="Componente1" title="Arduino Uno (Rev3)" id="20360"/>
  </connector>
 </net>
 <net>
  <connector id="connector1" name="A1">
   <part label="Componente1" title="Arduino Uno (Rev3)" id="20360"/>
  </connector>
 </net>
</netlist>
